edgenerator/__init__.py
edgenerator/ed_class.py
edgenerator/energy_leveler.py
edgenerator/main_program.py
edgenerator/prepare_input.py
edgenerator/profiles.py
edgenerator/read_excel.py
edgenerator/state_classes.py
edgenerator-1.0.1.dist-info/LICENSE
edgenerator-1.0.1.dist-info/METADATA
edgenerator-1.0.1.dist-info/WHEEL
edgenerator-1.0.1.dist-info/top_level.txt
edgenerator-1.0.1.dist-info/RECORD
